config/__init__.py
config/ieo - Copy.ini
config/ieo.ini
config/sample_ieo.ini
data/AIRT.cpg
data/AIRT.dbf
data/AIRT.prj
data/AIRT.sbn
data/AIRT.sbx
data/AIRT.shp
data/AIRT.shp.xml
data/AIRT.shx
data/Ireland_Sentinel2_tiles_ITM.cpg
data/Ireland_Sentinel2_tiles_ITM.dbf
data/Ireland_Sentinel2_tiles_ITM.prj
data/Ireland_Sentinel2_tiles_ITM.sbn
data/Ireland_Sentinel2_tiles_ITM.sbx
data/Ireland_Sentinel2_tiles_ITM.shp
data/Ireland_Sentinel2_tiles_ITM.shp.xml
data/Ireland_Sentinel2_tiles_ITM.shx
data/Ireland_WRS1_Landsat_1_3_ITM.cpg
data/Ireland_WRS1_Landsat_1_3_ITM.dbf
data/Ireland_WRS1_Landsat_1_3_ITM.prj
data/Ireland_WRS1_Landsat_1_3_ITM.sbn
data/Ireland_WRS1_Landsat_1_3_ITM.sbx
data/Ireland_WRS1_Landsat_1_3_ITM.shp
data/Ireland_WRS1_Landsat_1_3_ITM.shp.xml
data/Ireland_WRS1_Landsat_1_3_ITM.shx
data/Ireland_WRS2_Landsat_4_8_ITM.cpg
data/Ireland_WRS2_Landsat_4_8_ITM.dbf
data/Ireland_WRS2_Landsat_4_8_ITM.prj
data/Ireland_WRS2_Landsat_4_8_ITM.sbn
data/Ireland_WRS2_Landsat_4_8_ITM.sbx
data/Ireland_WRS2_Landsat_4_8_ITM.shp
data/Ireland_WRS2_Landsat_4_8_ITM.shp.xml
data/Ireland_WRS2_Landsat_4_8_ITM.shx
data/__init__.py
data/ieo.gdb/__init__.py
data/ieo.gdb/a00000001.TablesByName.atx
data/ieo.gdb/a00000001.gdbindexes
data/ieo.gdb/a00000001.gdbtable
data/ieo.gdb/a00000001.gdbtablx
data/ieo.gdb/a00000002.gdbtable
data/ieo.gdb/a00000002.gdbtablx
data/ieo.gdb/a00000003.gdbindexes
data/ieo.gdb/a00000003.gdbtable
data/ieo.gdb/a00000003.gdbtablx
data/ieo.gdb/a00000004.CatItemsByPhysicalName.atx
data/ieo.gdb/a00000004.CatItemsByType.atx
data/ieo.gdb/a00000004.FDO_UUID.atx
data/ieo.gdb/a00000004.gdbindexes
data/ieo.gdb/a00000004.gdbtable
data/ieo.gdb/a00000004.gdbtablx
data/ieo.gdb/a00000004.spx
data/ieo.gdb/a00000005.CatItemTypesByName.atx
data/ieo.gdb/a00000005.CatItemTypesByParentTypeID.atx
data/ieo.gdb/a00000005.CatItemTypesByUUID.atx
data/ieo.gdb/a00000005.gdbindexes
data/ieo.gdb/a00000005.gdbtable
ieo-1.1.1.dist-info/DESCRIPTION.rst
ieo-1.1.1.dist-info/LICENSE.txt
ieo-1.1.1.dist-info/METADATA
ieo-1.1.1.dist-info/RECORD
ieo-1.1.1.dist-info/WHEEL
ieo-1.1.1.dist-info/metadata.json
ieo-1.1.1.dist-info/top_level.txt
