Metadata-Version: 2.0
Name: ieo
Version: 1.1.1
Summary: Irish Earth Observation library.
Home-page: UNKNOWN
Author: Guy Serbin
Author-email: UNKNOWN
License: This work is licensed under the Creative Commons Attribution 4.0 International License. To view a copy of this license, visit http://creativecommons.org/licenses/by/4.0/ or send a letter to Creative Commons, PO Box 1866, Mountain View, CA 94042, USA.
Project-URL: Documentation, https://readthedocs.org/projects/ieo/
Project-URL: Source, https://github.com/Teagasc/ieo
Project-URL: Tracker, https://github.com/Teagasc/ieo/issues
Platform: UNKNOWN
Classifier: Programming Language :: Python
Classifier: Programming Language :: Python :: 2.7
Classifier: Programming Language :: Python :: 3
Classifier: Programming Language :: Python :: 3.1
Classifier: Programming Language :: Python :: 3.2
Classifier: Programming Language :: Python :: 3.3
Classifier: Programming Language :: Python :: 3.4
Classifier: Programming Language :: Python :: 3.5
Classifier: Programming Language :: Python :: 3.6
Classifier: Topic :: Scientific/Engineering :: GIS
Requires-Dist: numexpr
Requires-Dist: numpy
Requires-Dist: gdal
Requires-Dist: pillow
